{
    "description": "",
    "private": false,
    "successCode": {
        "outputKey": "purchaseConfirmation",
        "valuePath": "/purchaseReference"
    },
    "inputs": {
        "options": {
            "typeRef": "#/domains/PetInsurance/types/Options",
            "default": {},
            "initial": true
        },
        "url": {
            "typeRef": "#/domains/Generic/types/URL",
            "description": "Website entry point.",
            "initial": true
        },
        "pets": {
            "description": "Information about the pet (name, type, breed, gender, standard questions etc).",
            "typeRef": "#/domains/PetInsurance/types/Pets"
        },
        "selectedBreedType": {
            "typeRef": "#/domains/PetInsurance/types/BreedType",
            "description": "Selected breed typology (Pedigree, Non-Pedigree etc)",
            "sourceOutputKey": "availableBreedTypes",
            "inputMethod": "SelectOne"
        },
        "payment": {
            "typeRef": "#/domains/Generic/types/Payment"
        },
        "directDebit": {
            "typeRef": "#/domains/PetInsurance/types/DirectDebitPayment"
        },
        "owner": {
            "typeRef": "#/domains/PetInsurance/types/Owner",
            "description": "Details about the pet owner and address."
        },
        "panToken": {
            "typeRef": "#/domains/Generic/types/PanToken"
        },
        "account": {
            "typeRef": "#/domains/Generic/types/Account"
        },
        "finalPriceConsent": {
            "typeRef": "#/domains/Generic/types/PriceConsent",
            "description": "Client's consent for final price, should exactly match the <code>finalPrice</code> object from output.<br/>Automation will not proceed with placing order until the consent is provided.",
            "sourceOutputKey": "finalPrice",
            "inputMethod": "Consent"
        },
        "policyOptions": {
            "typeRef": "#/domains/PetInsurance/types/PolicyOption",
            "description": "Cover start date, number of pets owned, second policy holder(if any)."
        },
        "selectedVoluntaryExcess": {
            "typeRef": "#/domains/PetInsurance/types/VoluntaryExcess",
            "description": "Selected voluntary excess.",
            "sourceOutputKey": "availableVoluntaryExcesses",
            "inputMethod": "SelectOne"
        },
        "selectedAddress": {
            "typeRef": "#/domains/PetInsurance/types/Address",
            "sourceOutputKey": "availableAddresses",
            "description": "After postcode input a drop-down list with available addresses will appear. This input has the address selected from that list.",
            "inputMethod": "SelectOne"
        },
        "selectedCover": {
            "typeRef": "#/domains/PetInsurance/types/Cover",
            "description": "Selected protection cover.",
            "sourceOutputKey": "availableCovers",
            "inputMethod": "SelectOne"
        },
        "selectedCoverType": {
            "typeRef": "#/domains/PetInsurance/types/CoverType",
            "description": "Type of coverage.",
            "sourceOutputKey": "availableCoverTypes",
            "inputMethod": "SelectOne"
        },
        "selectedVetFee": {
            "typeRef": "#/domains/PetInsurance/types/VetFee",
            "description": "Vet fee amount covered.",
            "sourceOutputKey": "availableVetFees",
            "inputMethod": "SelectOne"
        },
        "selectedCoverOptions": {
            "typeRef": "#/domains/PetInsurance/types/CoverOptions",
            "description": "Optional extra packages.",
            "sourceOutputKey": "availableCoverOptions",
            "inputMethod": "SelectMany"
        },
        "selectedVetPaymentTerm": {
            "typeRef": "#/domains/PetInsurance/types/VetPaymentTerm",
            "description": "Terms of vet bill coverage.",
            "sourceOutputKey": "availableVetPaymentTerms",
            "inputMethod": "SelectOne"
        },
        "selectedPaymentTerm": {
            "typeRef": "#/domains/PetInsurance/types/PaymentTerm",
            "description": "Method of payment (card, directdebit etc).",
            "sourceOutputKey": "availablePaymentTerms",
            "inputMethod": "SelectOne"
        }
    },
    "outputs": {
        "estimatedPrice": {
            "description": "Emitted before asking for payment information.<br/>This is usually not the final amount to be paid, especially on websites which charge credit and company cards additionally. You will get <code>finalPrice</code> later.",
            "typeRef": "#/domains/Generic/types/PriceConsent"
        },
        "availableBreedTypes": {
            "typeRef": "#/domains/PetInsurance/types/BreedTypes",
            "description": "Available breed typologies (Pedigree, Non-Pedigree etc)."
        },
        "finalPrice": {
            "description": "Emitted immediately before placing order, when final price is available.<br/>Automation will request <code>finalPriceConsent</code> input which should match this object.",
            "typeRef": "#/domains/Generic/types/PriceConsent"
        },
        "availableVoluntaryExcesses": {
            "description": "Available voluntary excesses (in % increments).",
            "typeRef": "#/domains/PetInsurance/types/VoluntaryExcesses"
        },
        "availableAddresses": {
            "description": "Available addresses after postcode input.",
            "typeRef": "#/domains/PetInsurance/types/AddressesOrNull"
        },
        "availableCovers": {
            "description": "Available protection covers.",
            "typeRef": "#/domains/PetInsurance/types/Covers"
        },
        "availableCoverTypes": {
            "description": "Available types of coverage.",
            "typeRef": "#/domains/PetInsurance/types/CoverTypes"
        },
        "availableVetFees": {
            "description": "Availebel vet fee amounts covered.",
            "typeRef": "#/domains/PetInsurance/types/VetFees"
        },
        "availableCoverOptions": {
            "description": "Available optional extra packages.",
            "typeRef": "#/domains/PetInsurance/types/CoverOptions"
        },
        "availableVetPaymentTerms": {
            "description": "Available terms of vet bill coverage.",
            "typeRef": "#/domains/PetInsurance/types/VetPaymentTerms"
        },
        "availablePaymentTerms": {
            "description": "Available methods of payment (card, directdebit etc).",
            "typeRef": "#/domains/PetInsurance/types/PaymentTerms"
        },
        "insuranceProductInformationDocument": {
            "typeRef": "#/domains/Generic/types/StructuredTextItem",
            "description": "Emitted when the document information is presented."
        },
        "essentialInformation": {
            "typeRef": "#/domains/Generic/types/StructuredTextItem",
            "description": "Emitted when the esential information document is presented."
        },
        "policyWording": {
            "typeRef": "#/domains/Generic/types/StructuredTextItem",
            "description": "Emitted when the policy wording is presented."
        },
        "purchaseConfirmation": {
            "typeRef": "#/domains/PetInsurance/types/PurchaseConfirmation"
        },
        "availablePaymentDays": {
            "typeRef": "#/domains/PetInsurance/types/AvailablePaymentDays",
            "description": "List of available DD payment days."
        },
        "eligibilityConditions": {
            "typeRef": "#/domains/Generic/types/StructuredTextItem",
            "description": "Emitted when the eligibility conditions are presented."
        }
    },
    "types": {
        "Options": {
            "type": "object",
            "description": ""
        },
        "Pets": {
            "type": "array",
            "description": "An array with flags and informations about pets.",
            "pii": true,
            "minItems": 1,
            "items": {
                "$ref": "#/domains/PetInsurance/types/Pet"
            }
        },
        "Pet": {
            "type": "object",
            "description": "",
            "additionalProperties": false,
            "properties": {
                "name": {
                    "type": "string",
                    "description": "Pet Name",
                    "example": "Rex"
                },
                "animalType": {
                    "type": "string",
                    "description": "",
                    "example": "dog",
                    "enum": [
                        "dog",
                        "cat"
                    ]
                },
                "gender": {
                    "type": "string",
                    "description": "Animal gender.",
                    "example": "Male"
                },
                "breedType": {
                    "type": "string",
                    "description": "The record of descent of an animal (i.e. Cross Breed, Pedigree).",
                    "example": "Pedigree"
                },
                "breedName": {
                    "type": "string",
                    "description": "Your pet breed.",
                    "example": "Afgan",
                    "enum": [
                        "Affenpinscher",
                        "Afghan Hound",
                        "Afghan Shepherd",
                        "Aidi",
                        "Airedale Terrier",
                        "Akbash",
                        "Akita",
                        "Alano Español",
                        "Alaskan husky",
                        "Alaskan Klee Kai",
                        "Alaskan Malamute",
                        "Alaunt",
                        "Alopekis",
                        "Alpine Dachsbracke",
                        "Alpine Mastiff",
                        "Alpine Spaniel",
                        "American Akita",
                        "American Bully",
                        "American Bulldog",
                        "American Cocker Spaniel",
                        "American English Coonhound",
                        "American Eskimo Dog",
                        "American Foxhound",
                        "American Hairless Terrier",
                        "American Pit Bull Terrier",
                        "American Staffordshire Terrier",
                        "American Water Spaniel",
                        "Anatolian Shepherd Dog",
                        "Andalusian Hound",
                        "Anglo-Français de Petite Vénerie",
                        "Appenzeller Sennenhund",
                        "Argentine Polar Dog",
                        "Ariegeois",
                        "Armant",
                        "Armenian Gampr dog",
                        "Artois Hound",
                        "Australian Cattle Dog",
                        "Australian Kelpie",
                        "Australian Shepherd",
                        "Australian Stumpy Tail Cattle Dog",
                        "Australian Terrier",
                        "Austrian Black and Tan Hound",
                        "Austrian Pinscher",
                        "Azawakh",
                        "Bakharwal dog",
                        "Barbado da Terceira",
                        "Barbet",
                        "Basenji",
                        "Basque Shepherd Dog",
                        "Basset Artésien Normand",
                        "Basset Bleu de Gascogne",
                        "Basset Fauve de Bretagne",
                        "Basset Hound",
                        "Bavarian Mountain Hound",
                        "Beagle",
                        "Beagle-Harrier",
                        "Bearded Collie",
                        "Beauceron",
                        "Bedlington Terrier",
                        "Belgian Shepherd Dog (Groenendael)",
                        "Belgian Shepherd Dog (Laekenois)",
                        "Belgian Shepherd Dog (Malinois)",
                        "Belgian Shepherd Dog (Tervuren)",
                        "Bergamasco Shepherd",
                        "Berger Blanc Suisse",
                        "Berger Picard",
                        "Bernese Mountain Dog",
                        "Bichon Frisé",
                        "Billy",
                        "Black and Tan Coonhound",
                        "Black and Tan Virginia Foxhound",
                        "Black Norwegian Elkhound",
                        "Black Russian Terrier",
                        "Black Mouth Cur",
                        "Bloodhound",
                        "Blue Heeler",
                        "Blue Lacy",
                        "Blue Paul Terrier",
                        "Blue Picardy Spaniel",
                        "Bluetick Coonhound",
                        "Boerboel",
                        "Bohemian Shepherd",
                        "Bolognese",
                        "Border Collie",
                        "Border Terrier",
                        "Borzoi",
                        "Bosnian Coarse-haired Hound",
                        "Boston Terrier",
                        "Bouvier des Ardennes",
                        "Bouvier des Flandres",
                        "Boxer",
                        "Boykin Spaniel",
                        "Bracco Italiano",
                        "Braque d'Auvergne",
                        "Braque de l'Ariege",
                        "Braque du Bourbonnais",
                        "Braque du Puy",
                        "Braque Francais",
                        "Braque Saint-Germain",
                        "Brazilian Dogo",
                        "Brazilian Terrier",
                        "Briard",
                        "Briquet Griffon Vendéen",
                        "Brittany",
                        "Broholmer",
                        "Bruno Jura Hound",
                        "Brussels Griffon",
                        "Bucovina Shepherd Dog",
                        "Bull and Terrier",
                        "Bull Terrier",
                        "Bulldog",
                        "Bullenbeisser",
                        "Bullmastiff",
                        "Bully Kutta",
                        "Burgos Pointer",
                        "Cairn Terrier",
                        "Canaan Dog",
                        "Canadian Eskimo Dog",
                        "Cane Corso",
                        "Cantabrian Water Dog",
                        "Cão da Serra de Aires",
                        "Cão de Castro Laboreiro",
                        "Cão de Gado Transmontano",
                        "Cão Fila de São Miguel",
                        "Carolina Dog",
                        "Carpathian Shepherd Dog",
                        "Catalan Sheepdog",
                        "Caucasian Shepherd Dog",
                        "Cavalier King Charles Spaniel",
                        "Celtic Hound",
                        "Central Asian Shepherd Dog",
                        "Cesky Fousek",
                        "Cesky Terrier",
                        "Chesapeake Bay Retriever",
                        "Chien Français Blanc et Noir",
                        "Chien Français Blanc et Orange",
                        "Chien Français Tricolore",
                        "Chien-gris",
                        "Chihuahua",
                        "Chilean Terrier",
                        "Chinese Chongqing Dog",
                        "Chinese Crested Dog",
                        "Chinese Imperial Dog",
                        "Chinook",
                        "Chippiparai",
                        "Chiribaya Dog",
                        "Chow Chow",
                        "Cierny Sery",
                        "Cirneco dell'Etna",
                        "Clumber Spaniel",
                        "Collie, Rough",
                        "Collie, Smooth",
                        "Combai",
                        "Cordoba Fighting Dog",
                        "Coton de Tulear",
                        "Cretan Hound",
                        "Croatian Sheepdog",
                        "Cumberland Sheepdog",
                        "Curly-Coated Retriever",
                        "Cursinu",
                        "Czechoslovakian Wolfdog",
                        "Dachshund",
                        "Dalbo dog",
                        "Dalmatian",
                        "Dandie Dinmont Terrier",
                        "Danish-Swedish Farmdog",
                        "Deutsche Bracke",
                        "Doberman Pinscher",
                        "Dogo Argentino",
                        "Dogo Cubano",
                        "Dogue de Bordeaux",
                        "Drentse Patrijshond",
                        "Drever",
                        "Dunker",
                        "Dutch Shepherd",
                        "Dutch Smoushond",
                        "East Siberian Laika",
                        "East European Shepherd",
                        "Elo",
                        "English Cocker Spaniel",
                        "English Foxhound",
                        "English Mastiff",
                        "English Pointer",
                        "English Setter",
                        "English Shepherd",
                        "English Springer Spaniel",
                        "English Toy Terrier (Black & Tan)",
                        "English Water Spaniel",
                        "English White Terrier",
                        "Entlebucher Mountain Dog",
                        "Estonian Hound",
                        "Estrela Mountain Dog",
                        "Eurasier",
                        "Eurohound",
                        "Field Spaniel",
                        "Fila Brasileiro",
                        "Finnish Hound",
                        "Finnish Lapphund",
                        "Finnish Spitz",
                        "Flat-Coated Retriever",
                        "Fox Terrier, Smooth",
                        "Fox Terrier, Wire",
                        "French Brittany",
                        "French Bulldog",
                        "French Spaniel",
                        "Gaddi Kutta",
                        "Galgo Español",
                        "Galician Shepherd Dog",
                        "Garafian Shepherd",
                        "Gascon Saintongeois",
                        "Georgian Shepherd",
                        "German Longhaired Pointer",
                        "German Pinscher",
                        "German Roughhaired Pointer",
                        "German Shepherd Dog",
                        "German Shorthaired Pointer",
                        "German Spaniel",
                        "German Spitz",
                        "German Wirehaired Pointer",
                        "Giant Schnauzer",
                        "Glen of Imaal Terrier",
                        "Golden Retriever",
                        "Gordon Setter",
                        "Gran Mastín de Borínquen",
                        "Grand Anglo-Français Blanc et Noir",
                        "Grand Anglo-Français Blanc et Orange",
                        "Grand Anglo-Français Tricolore",
                        "Grand Basset Griffon Vendéen",
                        "Grand Bleu de Gascogne",
                        "Grand Griffon Vendéen",
                        "Great Dane",
                        "Great Pyrenees",
                        "Greater Swiss Mountain Dog",
                        "Greek Harehound",
                        "Greek Shepherd",
                        "Greenland Dog",
                        "Greyhound",
                        "Griffon Bleu de Gascogne",
                        "Griffon Fauve de Bretagne",
                        "Griffon Nivernais",
                        "Guatemalan Dogo",
                        "Gull Terrier",
                        "Hamiltonstövare",
                        "Hanover Hound",
                        "Hare Indian Dog",
                        "Harrier",
                        "Havanese",
                        "Hawaiian Poi Dog",
                        "Himalayan Sheepdog",
                        "Hokkaido",
                        "Hortaya borzaya",
                        "Hovawart",
                        "Huntaway",
                        "Hygen Hound",
                        "Ibizan Hound",
                        "Icelandic Sheepdog",
                        "Indian pariah dog",
                        "Indian Spitz",
                        "Irish Red and White Setter",
                        "Irish Setter",
                        "Irish Terrier",
                        "Irish Water Spaniel",
                        "Irish Wolfhound",
                        "Istrian Coarse-haired Hound",
                        "Istrian Short-haired Hound",
                        "Italian Greyhound",
                        "Jack Russell Terrier",
                        "Jagdterrier",
                        "Swedish Elkhound",
                        "Japanese Chin",
                        "Japanese Spitz",
                        "Japanese Terrier",
                        "Jindo",
                        "Jonangi",
                        "Kaikadi dog",
                        "Kai Ken",
                        "Kangal Shepherd Dog",
                        "Kanni",
                        "Karakachan dog",
                        "Karelian Bear Dog",
                        "Karst Shepherd",
                        "Keeshond",
                        "Kerry Beagle",
                        "Kerry Blue Terrier",
                        "King Charles Spaniel",
                        "King Shepherd",
                        "Kintamani",
                        "Kishu Ken",
                        "Komondor",
                        "Koolie",
                        "Koyun dog",
                        "Kromfohrländer",
                        "Kumaon Mastiff",
                        "Kunming Wolfdog",
                        "Kurī",
                        "Kuvasz",
                        "Kyi-Leo",
                        "Labrador Husky",
                        "Labrador Retriever",
                        "Lagotto Romagnolo",
                        "Lakeland Terrier",
                        "Lancashire Heeler",
                        "Landseer",
                        "Lapponian Herder",
                        "Lapponian Shepherd",
                        "Large Münsterländer",
                        "Leonberger",
                        "Lhasa Apso",
                        "Lithuanian Hound",
                        "Louisiana Catahoula Leopard Dog",
                        "Löwchen",
                        "Mackenzie River husky",
                        "Magyar agár",
                        "Mahratta Greyhound",
                        "Maltese",
                        "Maremma Sheepdog",
                        "Marquesan Dog",
                        "McNab dog",
                        "Miniature American Shepherd",
                        "Miniature Bull Terrier",
                        "Miniature Fox Terrier",
                        "Miniature Pinscher",
                        "Miniature Schnauzer",
                        "Miniature Shar Pei",
                        "Molossus",
                        "Molossus of Epirus",
                        "Montenegrin Mountain Hound",
                        "Moscow Watchdog",
                        "Moscow Water Dog",
                        "Mountain Cur",
                        "Mucuchies",
                        "Mudhol Hound",
                        "Mudi",
                        "Neapolitan Mastiff",
                        "Nederlandse Kooikerhondje",
                        "Nenets Herding Laika",
                        "Newfoundland",
                        "New Guinea singing dog",
                        "New Zealand Heading Dog",
                        "Norfolk Spaniel",
                        "Norfolk Terrier",
                        "Norrbottenspets",
                        "North Country Beagle",
                        "Northern Inuit Dog",
                        "Norwegian Buhund",
                        "Norwegian Elkhound",
                        "Norwegian Lundehund",
                        "Norwich Terrier",
                        "Nova Scotia Duck Tolling Retriever",
                        "Old Croatian Sighthound",
                        "Old Danish Pointer",
                        "Old English Bulldog",
                        "Old English Sheepdog",
                        "Old English Terrier",
                        "Old German Shepherd Dog",
                        "Old Spanish Pointer",
                        "Old Time Farm Shepherd",
                        "Old Welsh Grey Sheepdog",
                        "Olde English Bulldogge",
                        "Otterhound",
                        "Pachon Navarro",
                        "Pandikona",
                        "Paisley Terrier",
                        "Papillon",
                        "Parson Russell Terrier",
                        "Pastore della Lessinia e del Lagorai",
                        "Patterdale Terrier",
                        "Pekingese",
                        "Perro de Pastor Mallorquin",
                        "Perro de Presa Canario",
                        "Perro de Presa Mallorquin",
                        "Peruvian Inca Orchid",
                        "Petit Basset Griffon Vendéen",
                        "Petit Bleu de Gascogne",
                        "Phalène",
                        "Pharaoh Hound",
                        "Phu Quoc Ridgeback",
                        "Picardy Spaniel",
                        "Plummer Terrier",
                        "Plott Hound",
                        "Podenco Canario",
                        "Poitevin",
                        "Polish Greyhound",
                        "Polish Hound",
                        "Polish Hunting Dog",
                        "Polish Lowland Sheepdog",
                        "Polish Tatra Sheepdog",
                        "Pomeranian",
                        "Pont-Audemer Spaniel",
                        "Poodle",
                        "Porcelaine",
                        "Portuguese Podengo",
                        "Portuguese Pointer",
                        "Portuguese Water Dog",
                        "Posavac Hound",
                        "Potsdam Greyhound",
                        "Pražský Krysařík",
                        "Pudelpointer",
                        "Pug",
                        "Puli",
                        "Pumi",
                        "Pungsan dog",
                        "Pyrenean Mastiff",
                        "Pyrenean Shepherd",
                        "Rafeiro do Alentejo",
                        "Rajapalayam",
                        "Rampur Greyhound",
                        "Rastreador Brasileiro",
                        "Rat Terrier",
                        "Ratonero Bodeguero Andaluz",
                        "Ratonero Mallorquin",
                        "Ratonero Murciano de Huerta",
                        "Ratonero Valenciano",
                        "Redbone Coonhound",
                        "Rhodesian Ridgeback",
                        "Romanian Mioritic Shepherd Dog",
                        "Romanian Raven Shepherd Dog",
                        "Rottweiler",
                        "Russian Salon Dog",
                        "Russian Spaniel",
                        "Russian Toy",
                        "Russian Tracker",
                        "Russo-European Laika",
                        "Russell Terrier",
                        "Saarloos Wolfdog",
                        "Sabueso Español",
                        "Sabueso fino Colombiano",
                        "Saint Bernard",
                        "Saint John's water dog",
                        "Saint-Usuge Spaniel",
                        "Sakhalin Husky",
                        "Salish Wool Dog",
                        "Saluki",
                        "Samoyed",
                        "Sapsali",
                        "Šarplaninac",
                        "Schapendoes",
                        "Schillerstövare",
                        "Schipperke",
                        "Schweizer Laufhund",
                        "Schweizerischer Niederlaufhund",
                        "Scotch Collie",
                        "Scottish Deerhound",
                        "Scottish Terrier",
                        "Sealyham Terrier",
                        "Segugio Italiano",
                        "Segugio Maremmano",
                        "Seppala Siberian Sleddog",
                        "Serbian Hound",
                        "Serbian Tricolour Hound",
                        "Seskar Seal Dog",
                        "Shar Pei",
                        "Shetland Sheepdog",
                        "Shiba Inu",
                        "Shih Tzu",
                        "Shikoku",
                        "Shiloh Shepherd",
                        "Siberian Husky",
                        "Silken Windhound",
                        "Silky Terrier",
                        "Sinhala Hound",
                        "Skye Terrier",
                        "Sloughi",
                        "Slovakian Wirehaired Pointer",
                        "Slovensky Cuvac",
                        "Slovensky Kopov",
                        "Smålandsstövare",
                        "Small Münsterländer",
                        "Small Greek Domestic Dog",
                        "Smithfield",
                        "Soft-Coated Wheaten Terrier",
                        "South Russian Ovcharka",
                        "Southern Hound",
                        "Spanish Mastiff",
                        "Spanish Water Dog",
                        "Spinone Italiano",
                        "Sporting Lucas Terrier",
                        "Stabyhoun",
                        "Staffordshire Bull Terrier",
                        "Standard Manchester Terrier",
                        "Standard Schnauzer",
                        "Stephens Cur",
                        "Styrian Coarse-haired Hound",
                        "Sussex Spaniel",
                        "Swedish Lapphund",
                        "Swedish Vallhund",
                        "Tahitian Dog",
                        "Tahltan Bear Dog",
                        "Taigan",
                        "Taiwan Dog",
                        "Talbot Hound",
                        "Tamaskan Dog",
                        "Teddy Roosevelt Terrier",
                        "Telomian",
                        "Tenterfield Terrier",
                        "Terceira Mastiff",
                        "Thai Bangkaew Dog",
                        "Thai Ridgeback",
                        "Tibetan Mastiff",
                        "Tibetan Spaniel",
                        "Tibetan Terrier",
                        "Tornjak",
                        "Tosa",
                        "Toy Bulldog",
                        "Toy Fox Terrier",
                        "Toy Manchester Terrier",
                        "Toy Trawler Spaniel",
                        "Transylvanian Hound",
                        "Treeing Cur",
                        "Treeing Tennessee Brindle",
                        "Treeing Walker Coonhound",
                        "Trigg Hound",
                        "Turnspit",
                        "Tweed Water Spaniel",
                        "Tyrolean Hound",
                        "Cimarrón Uruguayo",
                        "Vanjari Hound",
                        "Villano de Las Encartaciones",
                        "Villanuco de Las Encartaciones",
                        "Vizsla",
                        "Volpino Italiano",
                        "Weimaraner",
                        "Welsh Corgi, Cardigan",
                        "Welsh Corgi, Pembroke",
                        "Welsh Hillman",
                        "Welsh Sheepdog",
                        "Welsh Springer Spaniel",
                        "Welsh Terrier",
                        "West Highland White Terrier",
                        "West Siberian Laika",
                        "Westphalian Dachsbracke",
                        "Wetterhoun",
                        "Whippet",
                        "White Shepherd",
                        "Wirehaired Pointing Griffon",
                        "Wirehaired Vizsla",
                        "Xiasi Dog",
                        "Xoloitzcuintli",
                        "Yakutian Laika",
                        "Yorkshire Terrier",

                        "Abyssinian",
                        "Aegean",
                        "American Curl",
                        "American Bobtail",
                        "American Shorthair",
                        "American Wirehair",
                        "Arabian Mau",
                        "Australian Mist",
                        "Asian",
                        "Asian Semi-longhair",
                        "Balinese",
                        "Bambino",
                        "Bengal",
                        "Birman",
                        "Bombay",
                        "Brazilian Shorthair",
                        "British Semi-longhair",
                        "British Shorthair",
                        "British Longhair",
                        "Burmese",
                        "Burmilla",
                        "Chantilly-Tiffany",
                        "Chartreux",
                        "Chausie",
                        "Cheetoh",
                        "Colorpoint Shorthair",
                        "Javanese",
                        "Cornish Rex",
                        "Cymric",
                        "Cyprus",
                        "Egyptian Mau",
                        "European Shorthair",
                        "Exotic Shorthair",
                        "German Rex",
                        "Havana Brown",
                        "Himalayan",
                        "Japanese Bobtail",
                        "Khao Manee",
                        "Korat",
                        "Korean Bobtail",
                        "Kurilian Bobtail",
                        "LaPerm",
                        "Lykoi",
                        "Maine Coon",
                        "Manx",
                        "Minskin",
                        "Munchkin",
                        "Nebelung",
                        "Napoleon",
                        "Norwegian Forest Cat",
                        "Ocicat",
                        "Ojos Azules",
                        "Oregon Rex",
                        "Oriental Bicolor",
                        "Oriental Shorthair",
                        "Oriental Longhair",
                        "Pixie-bob",
                        "Raas",
                        "Ragamuffin",
                        "Russian Blue",
                        "Savannah",
                        "Selkirk Rex",
                        "Serengeti",
                        "Siamese",
                        "Thai",
                        "Siberian",
                        "Singapura",
                        "Snowshoe",
                        "Sokoke",
                        "Somali",
                        "Sphynx",
                        "Suphalak",
                        "Thai Lilac",
                        "Tonkinese",
                        "Toyger",
                        "Turkish Angora",
                        "Turkish Van",
                        "York Chocolate"
                    ]
                },
                "dateOfBirth": {
                    "type": "string",
                    "description": "Date of birth in YYYY-MM-DD format.",
                    "format": "date",
                    "example": "1976-01-27"
                },
                "petPrice": {
                    "type": "string",
                    "default": "",
                    "description": "The price given for the pet."
                },
                "relatedQuestions": {
                    "properties": {
                        "isSpayedOrNeutered": {
                            "type": "boolean"
                        },
                        "hasChipOrTag": {
                            "type": "boolean"
                        },
                        "isKeptAtYourAddress": {
                            "type": "boolean"
                        },
                        "hasLegalAction": {
                            "type": "boolean"
                        },
                        "hasBehaviourComplains": {
                            "type": "boolean"
                        },
                        "isIndoor": {
                            "type": "boolean"
                        },
                        "isYourPetHealthy": {
                            "type": "boolean"
                        }
                    },
                    "required": [
                        "isSpayedOrNeutered",
                        "hasChipOrTag",
                        "isKeptAtYourAddress",
                        "hasLegalAction",
                        "hasBehaviourComplains",
                        "isIndoor",
                        "isYourPetHealthy"
                    ],
                    "additionalProperties": false
                }
            },
            "required": [
                "name",
                "animalType",
                "gender",
                "breedName",
                "dateOfBirth",
                "relatedQuestions"
            ]
        },
        "BreedTypes": {
            "type": "array",
            "description": "",
            "minItems": 1,
            "items": {
                "$ref": "#/domains/PetInsurance/types/BreedType"
            }
        },
        "BreedType": {
            "type": "string",
            "description": ""
        },
        "PolicyOption": {
            "type": "object",
            "description": "",
            "properties": {
                "coverStartDate": {
                    "type": "string",
                    "description": "Cover Start Date.",
                    "example": "2019-04-02"
                },
                "numberOfPetsOwned": {
                    "type": "number",
                    "description": "",
                    "example": "2019-04-02"
                },
                "isJointPolicyHolder": {
                    "type": "boolean",
                    "default": false
                }
            },
            "required": [
                "coverStartDate",
                "numberOfPetsOwned",
                "isJointPolicyHolder"
            ],
            "additionalProperties": false
        },
        "Address": {
            "type": "string"
        },
        "Addresses": {
            "type": "array",
            "description": "",
            "pii": true,
            "minItems": 1,
            "items": {
                "$ref": "#/domains/PetInsurance/types/Address"
            }
        },
        "AddressesOrNull": {
            "oneOf": [
                {
                    "$ref": "#/domains/PetInsurance/types/Addresses"
                },
                {
                    "type": "null"
                }
            ]
        },
        "Cover": {
            "type": "string",
            "description": ""
        },
        "Covers": {
            "type": "array",
            "description": "",
            "minItems": 1,
            "items": {
                "$ref": "#/domains/PetInsurance/types/Cover"
            }
        },
        "MaritalStatusOption": {
            "type": "string",
            "description": "",
            "enum": [
                "Civil Partner",
                "Cohabiting",
                "Divorced",
                "Married",
                "Separated",
                "Single",
                "Widowed"
            ]
        },
        "VoluntaryExcesses": {
            "type": "array",
            "description": "",
            "minItems": 1,
            "items": {
                "$ref": "#/domains/PetInsurance/types/VoluntaryExcess"
            }
        },
        "VoluntaryExcess": {
            "type": "object",
            "description": "",
            "additionalProperties": false,
            "properties": {
                "name": {
                    "type": "string",
                    "description": "",
                    "example": "dog"
                },
                "details": {
                    "type": "string",
                    "description": ""
                },
                "priceLine": {
                    "type": "string",
                    "description": "",
                    "example": "Afgan"
                }
            },
            "required": [
                "name",
                "details",
                "priceLine"
            ]
        },
        "CoverTypes": {
            "type": "array",
            "description": "",
            "minItems": 1,
            "items": {
                "$ref": "#/domains/PetInsurance/types/CoverType"
            }
        },
        "CoverType": {
            "type": "object",
            "description": "",
            "additionalProperties": false,
            "properties": {
                "coverName": {
                    "type": "string",
                    "description": "",
                    "example": "Accident Only"
                },
                "price": {
                    "$ref": "#/domains/Generic/types/Price"
                }
            },
            "required": [
                "coverName",
                "price"
            ]
        },
        "VetPaymentTerms": {
            "type": "array",
            "description": "List of vet payment terms options.",
            "minItems": 1,
            "items": {
                "$ref": "#/domains/PetInsurance/types/VetPaymentTerm"
            }
        },
        "VetPaymentTerm": {
            "type": "string",
            "description": "Vet payment terms (i.e. Short-term & ongoing treatments, Short-term treatments)."
        },
        "PaymentTerms": {
            "type": "array",
            "description": "List of payment terms.",
            "example": "monthly-card",
            "minItems": 1,
            "items": {
                "$ref": "#/domains/PetInsurance/types/PaymentTerm"
            }
        },
        "PaymentTerm": {
            "type": "string",
            "description": "Payment term. The outlier is <strong>monthly-directdebit-card</strong>, which specifies that card payment must be used to pay the initial deposit, but direct debit must be set up for recurring monthly payments.",
            "enum": [
                "annual-card",
                "monthly-card",
                "monthly-directdebit",
                "monthly-directdebit-card"
            ]
        },
        "Payment": {
            "type": "object",
            "description": "Payment information, including card details and billing address.",
            "pii": true,
            "properties": {
                "person": {
                    "$ref": "#/domains/Generic/types/Person"
                },
                "card": {
                    "$ref": "#/domains/Generic/types/PaymentCard"
                },
                "address": {
                    "$ref": "#/domains/Generic/types/Address"
                },
                "selectedPaymentDay": {
                    "type": "string",
                    "description": "Preferred payment day, one of availableCardPaymentDays.",
                    "example": "10"
                }
            },
            "required": [
                "card",
                "person",
                "address"
            ],
            "additionalProperties": false
        },
        "DirectDebitPayment": {
            "type": "object",
            "description": "Account details for direct debit.",
            "pii": true,
            "properties": {
                "sortCode": {
                    "type": "string",
                    "description": "Bank sort code.",
                    "pattern": "\\d{2}-?\\d{2}-?\\d{2}",
                    "example": "56-00-29"
                },
                "accountNumber": {
                    "type": "string",
                    "minLength": 8,
                    "maxLength": 8,
                    "description": "The primary identifier for ownership of an bank account.",
                    "example": "26207729"
                },
                "accountHolder": {
                    "$ref": "#/domains/Generic/types/Person"
                },
                "accountHolderAddress": {
                    "$ref": "#/domains/Generic/types/Address"
                },
                "selectedPaymentDay": {
                    "type": "string",
                    "description": "Preferred payment day, one of availablePaymentDays.",
                    "example": "10"
                }
            },
            "required": [
                "sortCode",
                "accountNumber",
                "accountHolder",
                "accountHolderAddress"
            ],
            "additionalProperties": false
        },
        "VetFee": {
            "type": "object",
            "additionalProperties": false,
            "description": "",
            "properties": {
                "text": {
                    "type": "string",
                    "description": "",
                    "example": "Accident Only"
                },
                "price": {
                    "$ref": "#/domains/Generic/types/Price"
                }
            },
            "required": [
                "text",
                "price"
            ]
        },
        "AvailablePaymentDays": {
            "type": "array",
            "description": "List of payment days.",
            "items": {
                "type": "string"
            }
        },
        "VetFees": {
            "type": "array",
            "description": "",
            "minItems": 1,
            "items": {
                "$ref": "#/domains/PetInsurance/types/VetFee"
            }
        },
        "CoverOptions": {
            "type": "array",
            "description": "",
            "minItems": 1,
            "items": {
                "$ref": "#/domains/PetInsurance/types/CoverOption"
            }
        },
        "CoverOption": {
            "type": "object",
            "description": "",
            "additionalProperties": false,
            "properties": {
                "name": {
                    "type": "string",
                    "description": "",
                    "example": "dog"
                },
                "details": {
                    "type": "string",
                    "description": "",
                    "example": "Male"
                },
                "price": {
                    "$ref": "#/domains/Generic/types/Price"
                }
            },
            "required": [
                "name",
                "details",
                "price"
            ]
        },
        "Owner": {
            "type": "object",
            "pii": true,
            "additionalProperties": false,
            "properties": {
                "person": {
                    "type": "object",
                    "description": "Basic information about person's identity.",
                    "properties": {
                        "title": {
                            "type": "string",
                            "description": "",
                            "enum": [
                                "mr",
                                "miss",
                                "ms",
                                "mrs"
                            ]
                        },
                        "firstName": {
                            "type": "string",
                            "description": "First name(s) or given name(s), as specified in ID.",
                            "minLength": 1,
                            "example": "Bob"
                        },
                        "middleName": {
                            "type": "string",
                            "default": "",
                            "description": "Middle name, if applicable.<br/>This will only be used on websites which provide separate entry for middle names, otherwise it will be ignored.<br/>If middle name is essential for placing order, consider appending it to <code>firstName</code>."
                        },
                        "lastName": {
                            "type": "string",
                            "description": "Last name or surname, as specified in ID.",
                            "minLength": 1,
                            "example": "Smith"
                        },
                        "dateOfBirth": {
                            "type": "string",
                            "description": "Proposer's date of birth in YYYY-MM-DD format.",
                            "format": "date",
                            "example": "1976-01-27"
                        },
                        "maritalStatus": {
                            "type": "string",
                            "description": "Marital status of the owner.",
                            "example": "Single",
                            "enum": [
                                "Civil Partner",
                                "Cohabiting",
                                "Divorced",
                                "Married",
                                "Separated",
                                "Single",
                                "Widowed"
                            ]
                        }
                    },
                    "required": [
                        "title",
                        "firstName",
                        "lastName",
                        "dateOfBirth",
                        "maritalStatus"
                    ]
                },
                "address": {
                    "postcode": {
                        "type": "string",
                        "description": "Postcode in country-specific format, e.g. 5-digit number in US or <code>E3 3RP</code> in UK.",
                        "minLength": 1,
                        "example": "E3 3RP"
                    },
                    "propertyNumber": {
                        "type": "string",
                        "description": "Property number from owner's address.",
                        "minLength": 1
                    },
                    "required": [
                        "postcode",
                        "propertyNumber"
                    ]
                }
            }
        },
        "PurchaseConfirmation": {
            "type": "object",
            "description": "Information gathered on the \"confirmation\" page.",
            "additionalProperties": false,
            "properties": {
                "purchaseReference": {
                    "type": "string",
                    "description": "Reference code grabbed from the page.",
                    "example": "RL2XYZ"
                },
                "message": {
                    "type": "string",
                    "description": "The confirmation message.",
                    "example": "Thank you for using UBIO Insurance. Your quote is ABC123 and purchase reference is DEF456."
                },
                "price": {
                    "$ref": "#/domains/Generic/types/Price",
                    "description": "Price, if found on the confirmation page."
                }
            },
            "required": [
                "purchaseReference",
                "message",
                "price"
            ]
        },
        "StructuredTextItem": {
            "oneOf": [{
                    "$ref": "#/domains/Generic/types/StructuredText"
                },
                {
                    "$ref": "#/domains/Generic/types/File"
                },
                {
                    "$ref": "#/domains/Generic/types/Link"
                },
                {
                    "$ref": "#/domains/Generic/types/NamedText"
                },
                {
                    "$ref": "#/domains/Generic/types/HTML"
                },
                {
                    "$ref": "#/domains/Generic/types/Text"
                }
            ]
        }
    },
    "errors": [{
            "code": "QuoteNotFound",
            "category": "client",
            "description": "Given quote was not found by the insurer."
        },
        {
            "code": "RegistrationNumberInvalid",
            "category": "client",
            "description": "Registration number is not accepted by the website."
        },
        {
            "code": "RegistrationNumberRequired",
            "category": "client",
            "description": "Registration number is required by the website."
        },
        {
            "code": "PolicyAlreadyPurchased",
            "category": "client",
            "description": "The policy has already been purchased."
        },
        {
            "code": "DirectDebitRejected",
            "category": "client",
            "description": "Direct debit details provided have been rejected by the website."
        },
        {
            "code": "BreedTypeRequired",
            "category": "client",
            "description": "Breed type is required by the website."
        }
    ]
}
